fastfastqvalidation-0.1.0.dist-info/METADATA
fastfastqvalidation-0.1.0.dist-info/WHEEL
fq/__init__.py
fq/fq.cpython-314-x86_64-linux-gnu.so
fastfastqvalidation-0.1.0.dist-info/RECORD
