Metadata-Version: 2.4
Name: fastfastqvalidation
Version: 0.1.0
Classifier: Programming Language :: Rust
Classifier: Programming Language :: Python :: Implementation :: CPython
Classifier: Programming Language :: Python :: Implementation :: PyPy
Requires-Dist: maturin[patchelf]>=1.9.0
Requires-Python: >=3.8
